odoo/addons/switchboard_somconnexio/CHANGELOG.md
odoo/addons/switchboard_somconnexio/README.rst
odoo/addons/switchboard_somconnexio/__init__.py
odoo/addons/switchboard_somconnexio/__manifest__.py
odoo/addons/switchboard_somconnexio/data/product_attribute.xml
odoo/addons/switchboard_somconnexio/data/product_attribute_value.xml
odoo/addons/switchboard_somconnexio/data/product_category.xml
odoo/addons/switchboard_somconnexio/data/product_category_technology_supplier.xml
odoo/addons/switchboard_somconnexio/data/product_product.xml
odoo/addons/switchboard_somconnexio/data/product_template.xml
odoo/addons/switchboard_somconnexio/data/product_template_attribute_line_data.xml
odoo/addons/switchboard_somconnexio/data/service_supplier.xml
odoo/addons/switchboard_somconnexio/data/service_technology.xml
odoo/addons/switchboard_somconnexio/data/service_technology_service_supplier.xml
odoo/addons/switchboard_somconnexio/demo/contract.xml
odoo/addons/switchboard_somconnexio/demo/products.xml
odoo/addons/switchboard_somconnexio/i18n/ca_ES.po
odoo/addons/switchboard_somconnexio/i18n/es.po
odoo/addons/switchboard_somconnexio/listeners/__init__.py
odoo/addons/switchboard_somconnexio/listeners/contract_line_listener.py
odoo/addons/switchboard_somconnexio/models/__init__.py
odoo/addons/switchboard_somconnexio/models/contract_contract.py
odoo/addons/switchboard_somconnexio/models/crm_lead.py
odoo/addons/switchboard_somconnexio/models/crm_lead_line.py
odoo/addons/switchboard_somconnexio/models/contract_info/__init__.py
odoo/addons/switchboard_somconnexio/models/contract_info/switchboard_service_contract_info.py
odoo/addons/switchboard_somconnexio/models/isp_info/__init__.py
odoo/addons/switchboard_somconnexio/models/isp_info/switchboard_isp_info.py
odoo/addons/switchboard_somconnexio/opencell_models/__init__.py
odoo/addons/switchboard_somconnexio/opencell_models/subscription_from_contract.py
odoo/addons/switchboard_somconnexio/otrs_factories/__init__.py
odoo12_addon_switchboard_somconnexio-12.0.1.0.1.dist-info/METADATA
odoo12_addon_switchboard_somconnexio-12.0.1.0.1.dist-info/WHEEL
odoo12_addon_switchboard_somconnexio-12.0.1.0.1.dist-info/top_level.txt
odoo12_addon_switchboard_somconnexio-12.0.1.0.1.dist-info/RECORD
