Metadata-Version: 2.1
Name: odoo12-addon-switchboard-somconnexio
Version: 12.0.1.0.1
Summary: Odoo Som Connexió Switchboard technology
Home-page: https://coopdevs.org
Author: Coopdevs Treball SCCL, Som Connexió SCCL
License: AGPL-3
Platform: UNKNOWN
Classifier: Programming Language :: Python
Classifier: Framework :: Odoo
Classifier: Framework :: Odoo :: 12.0
Classifier: License :: OSI Approved :: GNU Affero General Public License v3
Requires-Python: >=3.5
Requires-Dist: faker
Requires-Dist: odoo12-addon-somconnexio
Requires-Dist: odoo <12.1dev,>=12.0a
Requires-Dist: openupgradelib
Requires-Dist: otrs-somconnexio
